cybercafe/__init__.py
cybercafe/client.py
cybercafe/controllers/__init__.py
cybercafe/controllers/clipboard.py
cybercafe/controllers/files.py
cybercafe/controllers/keyboard.py
cybercafe/controllers/mouse.py
cybercafe/controllers/powershell.py
cybercafe/controllers/screen.py
cybercafe/errors/SpaceError.py
cybercafe/models/__init__.py
cybercafe/models/space.py
cybercafe/utils/request.py
cybercafe-0.1.3.dist-info/METADATA
cybercafe-0.1.3.dist-info/WHEEL
cybercafe-0.1.3.dist-info/top_level.txt
cybercafe-0.1.3.dist-info/RECORD
