Metadata-Version: 2.4
Name: cybercafe
Version: 0.1.3
Summary: Cybercafe Python Library
Author-email: Brian Lemayian <brianlemayian11@gmail.com>
Classifier: Programming Language :: Python :: 3
Classifier: License :: OSI Approved :: MIT License
Classifier: Operating System :: OS Independent
Requires-Python: >=3.8
Requires-Dist: httpx>=0.25.0
